adventurous_gauging_koplik/__init__.py
adventurous_gauging_koplik/data_conversion.py
adventurous_gauging_koplik/model.py
adventurous_gauging_koplik/train_setup.py
adventurous_gauging_koplik-0.1.1.dist-info/LICENSE
adventurous_gauging_koplik-0.1.1.dist-info/METADATA
adventurous_gauging_koplik-0.1.1.dist-info/WHEEL
adventurous_gauging_koplik-0.1.1.dist-info/top_level.txt
adventurous_gauging_koplik-0.1.1.dist-info/RECORD
